[
	{
		"title": "Inspection de toitures",
		"icon": "eye",
		"description": "Detection precoce des desordres : fissures, decollements, infiltrations, vegetation. Rapport illustre avec localisation precise.",
		"category": "Batiment"
	},
	{
		"title": "Inspection de facades",
		"icon": "rectangle-stack",
		"description": "Analyse complete des revetements, joints, fenetres et elements de facade. Ideal pour diagnostics prealables.",
		"category": "Batiment"
	},
	{
		"title": "Ouvrages d art et structures",
		"icon": "cliboard-document-check",
		"description": "Inspection de ponts, viaducs, pylones, cheminees et reservoirs. Documentation sans interruption de service.",
		"category": "Industrie"
	},
	{
		"title": "Thermographie infrarouge",
		"icon": "bolt",
		"description": "Camera thermique pour detecter deperditions energetiques, humidite cachee, ponts thermiques et defauts electriques.",
		"category": "Batiment"
	},
	{
		"title": "Topographie et metre",
		"icon": "document-chart-bar",
		"description": "Releves topographiques RTK avec precision centimetrique. Calcul de surfaces, volumes et distances.",
		"category": "Geomatique"
	},
	{
		"title": "Orthophotographie",
		"icon": "squares-plus",
		"description": "Mosaiques orthorectifiees georeferencees a tres haute resolution pour suivi de chantier ou amenagement.",
		"category": "Geomatique"
	},
	{
		"title": "Modelisation 3D",
		"icon": "cube-transparent",
		"description": "Reconstruction photogrammetrique de batiments et sites industriels. Nuages de points et modeles BIM.",
		"category": "Geomatique"
	},
	{
		"title": "Inspection panneaux solaires",
		"icon": "sun",
		"description": "Audit thermique de centrales photovoltaiques pour detecter cellules defaillantes ou hot spots.",
		"category": "Industrie"
	},
	{
		"title": "Suivi de chantier",
		"icon": "clipboard-document-list",
		"description": "Capture reguliere pour documenter l avancement d un chantier et produire des etats des lieux dates.",
		"category": "Batiment"
	},
	{
		"title": "Inspection de reseaux",
		"icon": "circle-stack",
		"description": "Surveillance de lignes electriques, gazoducs et canalisations. Detection de corrosion ou deformations.",
		"category": "Industrie"
	},
	{
		"title": "Rapport professionnel",
		"icon": "document-text",
		"description": "Livrables cles en main : rapport PDF annote, orthophotos, videos HD et donnees SIG sous 48h.",
		"category": "Livrables"
	},
	{
		"title": "Certifications et conformite",
		"icon": "shield-check",
		"description": "Telepilote certifie DGAC, operateur UAS enregistre. Missions conformes a la reglementation EU 2019/947.",
		"category": "Securite"
	}
]